tyler/__init__.py
tyler/cli/__init__.py
tyler/cli/chat.py
tyler/cli/main.py
tyler/database/__init__.py
tyler/database/cli.py
tyler/database/config.py
tyler/database/models.py
tyler/database/storage_backend.py
tyler/database/thread_store.py
tyler/database/migrations/alembic.ini
tyler/database/migrations/env.py
tyler/database/migrations/script.py.mako
tyler/database/migrations/versions/20250206_0505_197750e12029_initial.py
tyler/database/migrations/versions/20250206_0506_197750e12030_add_reactions.py
tyler/database/migrations/versions/20250207_0101_197750e12031_add_platforms.py
tyler/database/migrations/versions/20250208_0000_197750e12032_migrate_json_to_jsonb.py
tyler/mcp/__init__.py
tyler/mcp/server_manager.py
tyler/mcp/service.py
tyler/mcp/utils.py
tyler/models/__init__.py
tyler/models/agent.py
tyler/models/attachment.py
tyler/models/message.py
tyler/models/thread.py
tyler/storage/__init__.py
tyler/storage/file_store.py
tyler/tools/__init__.py
tyler/tools/audio.py
tyler/tools/browser.py
tyler/tools/command_line.py
tyler/tools/files.py
tyler/tools/image.py
tyler/tools/notion.py
tyler/tools/slack.py
tyler/tools/web.py
tyler/utils/__init__.py
tyler/utils/agent_runner.py
tyler/utils/files.py
tyler/utils/logging.py
tyler/utils/registry.py
tyler/utils/tool_runner.py
tyler_agent-1.1.0.dist-info/METADATA
tyler_agent-1.1.0.dist-info/WHEEL
tyler_agent-1.1.0.dist-info/entry_points.txt
tyler_agent-1.1.0.dist-info/licenses/LICENSE
tyler_agent-1.1.0.dist-info/RECORD
