Metadata-Version: 2.4
Name: tyler-agent
Version: 1.1.0
Summary: Tyler: A development kit for manifesting AI agents with a complete lack of conventional limitations
Project-URL: Homepage, https://github.com/adamwdraper/tyler
Project-URL: Documentation, https://github.com/adamwdraper/tyler#readme
Project-URL: Repository, https://github.com/adamwdraper/tyler
Project-URL: Bug Tracker, https://github.com/adamwdraper/tyler/issues
Author: adamwdraper
License: CC BY-NC 4.0
License-File: LICENSE
Classifier: Development Status :: 3 - Alpha
Classifier: Intended Audience :: Developers
Classifier: License :: Free for non-commercial use
Classifier: Operating System :: OS Independent
Classifier: Programming Language :: Python :: 3
Classifier: Programming Language :: Python :: 3.12
Requires-Python: >=3.12
Requires-Dist: aiohttp>=3.11.11
Requires-Dist: aiosqlite>=0.21.0
Requires-Dist: alembic>=1.14.1
Requires-Dist: asyncpg>=0.30.0
Requires-Dist: backoff>=2.2.1
Requires-Dist: beautifulsoup4>=4.12.0
Requires-Dist: click>=8.1.8
Requires-Dist: greenlet>=3.1.1
Requires-Dist: httpx>=0.27.2
Requires-Dist: huggingface-hub>=0.27.0
Requires-Dist: litellm>=1.60.2
Requires-Dist: openai>=1.61.0
Requires-Dist: pandas>=2.2.3
Requires-Dist: pdf2image>=1.17.0
Requires-Dist: pillow>=11.0.0
Requires-Dist: psycopg2-binary>=2.9.9
Requires-Dist: pydantic>=2.10.4
Requires-Dist: pypdf>=5.3.0
Requires-Dist: python-dotenv>=1.0.1
Requires-Dist: python-magic>=0.4.0
Requires-Dist: requests>=2.32.3
Requires-Dist: slack-sdk>=3.34.0
Requires-Dist: sqlalchemy>=2.0.36
Requires-Dist: tiktoken>=0.8.0
Requires-Dist: uuid-utils>=0.10.0
Requires-Dist: wandb>=0.19.1
Requires-Dist: weave>=0.51.32
Provides-Extra: dev
Requires-Dist: coverage>=7.6.10; extra == 'dev'
Requires-Dist: pip-tools>=7.4.1; extra == 'dev'
Requires-Dist: pipdeptree>=2.25.0; extra == 'dev'
Requires-Dist: pytest-asyncio>=0.25.2; extra == 'dev'
Requires-Dist: pytest-cov>=6.0.0; extra == 'dev'
Requires-Dist: pytest>=8.3.4; extra == 'dev'
